{
  "project_info": {
    "project_number": "407660574749",
    "project_id": "hamel-421cb",
    "storage_bucket": "hamel-421cb.appspot.com"
  },
  "client": [
    {
      "client_info": {
        "mobilesdk_app_id": "1:407660574749:android:21bdc234ee5a57edafaef4",
        "android_client_info": {
          "package_name": "com.hamel.hamel"
        }
      },
      "oauth_client": [
        {
          "client_id": "407660574749-eumtri42lctm8pfl42pa3kbfsrdlmhs6.apps.googleusercontent.com",
          "client_type": 1,
          "android_info": {
            "package_name": "com.hamel.hamel",
            "certificate_hash": "9a33849c6c9ff582f11adf2beb3bfa5f07c5b9af"
          }
        },
        {
          "client_id": "407660574749-g48ja4j093q6kq0rohud4eper2qd71se.apps.googleusercontent.com",
          "client_type": 3
        }
      ],
      "api_key": [
        {
          "current_key": "AIzaSyAD0ZCAbbdVnbfkPvJ2jy9yoKy14C-TUg4"
        }
      ],
      "services": {
        "appinvite_service": {
          "other_platform_oauth_client": [
            {
              "client_id": "407660574749-g48ja4j093q6kq0rohud4eper2qd71se.apps.googleusercontent.com",
              "client_type": 3
            }
          ]
        }
      }
    }
  ],
  "configuration_version": "1"
}